Metadata-Version: 1.1
Name: AlignQC
Version: 2.0.5
Summary: Python and R based tool for assessing the quality of alignments
Home-page: https://github.com/jason-weirather/AlignQC
Author: Jason L Weirather
Author-email: jason.weirather@gmail.com
License: Apache License, Version 2.0
Keywords: bioinformatics,sequence,alignment
Platform: UNKNOWN
Classifier: Development Status :: 3 - Alpha
Classifier: Intended Audience :: Science/Research
Classifier: Topic :: Scientific/Engineering :: Bio-Informatics
Classifier: License :: OSI Approved :: Apache Software License
